{
  "uid" : "3f020dcbd370bc3b",
  "name" : "",
  "fullName" : "Signup to My Store, Do login and Buy a Product: As a user, I can signup to website.",
  "historyId" : "d1179049e73394a6d7b6b32c9a4adf16",
  "time" : {
    "start" : 1620226892366,
    "stop" : 1620226892369,
    "duration" : 3
  },
  "description" : "",
  "descriptionHtml" : "",
  "status" : "passed",
  "flaky" : false,
  "newFailed" : false,
  "beforeStages" : [ ],
  "afterStages" : [ ],
  "labels" : [ {
    "name" : "framework",
    "value" : "wdio"
  }, {
    "name" : "language",
    "value" : "javascript"
  }, {
    "name" : "thread",
    "value" : "0-0"
  }, {
    "name" : "suite",
    "value" : "Signup to My Store, Do login and Buy a Product: As a user, I can signup to website"
  }, {
    "name" : "testClass",
    "value" : "Signup to My Store, Do login and Buy a Product: As a user, I can signup to website"
  }, {
    "name" : "testMethod",
    "value" : ""
  }, {
    "name" : "package",
    "value" : "Signup to My Store, Do login and Buy a Product: As a user, I can signup to website"
  }, {
    "name" : "resultFormat",
    "value" : "allure1"
  } ],
  "parameters" : [ {
    "name" : "browser",
    "value" : "chrome-90.0.4430.93"
  } ],
  "links" : [ ],
  "hidden" : true,
  "retry" : true,
  "extra" : {
    "categories" : [ ],
    "tags" : [ ]
  },
  "source" : "3f020dcbd370bc3b.json",
  "parameterValues" : [ "chrome-90.0.4430.93" ]
}